grz_pydantic_models/__init__.py
grz_pydantic_models/common.py
grz_pydantic_models/dates.py
grz_pydantic_models/py.typed
grz_pydantic_models/std.py
grz_pydantic_models/mii/__init__.py
grz_pydantic_models/mii/consent.py
grz_pydantic_models/pruefbericht/__init__.py
grz_pydantic_models/pruefbericht/v0.py
grz_pydantic_models/resources/thresholds.json
grz_pydantic_models/submission/__init__.py
grz_pydantic_models/submission/metadata/__init__.py
grz_pydantic_models/submission/metadata/v1.py
grz_pydantic_models/submission/metadata/versioning.py
grz_pydantic_models/submission/thresholds/__init__.py
grz_pydantic_models/submission/thresholds/v1.py
grz_pydantic_models-2.5.0.dist-info/METADATA
grz_pydantic_models-2.5.0.dist-info/WHEEL
grz_pydantic_models-2.5.0.dist-info/licenses/LICENSE
grz_pydantic_models-2.5.0.dist-info/RECORD
