Metadata-Version: 2.4
Name: grz-pydantic-models
Version: 2.5.0
Summary: Pydantic models for the GRZ metadata schema
Project-URL: Homepage, https://github.com/BfArM-MVH/grz-tools
Project-URL: Repository, https://github.com/BfArM-MVH/grz-tools
Project-URL: Documentation, https://github.com/BfArM-MVH/grz-tools/tree/main/packages/grz-pydantic-models
Project-URL: Issues, https://github.com/BfArM-MVH/grz-tools/issues
Author-email: Koray Kirli <koraykirli@gmail.com>, Mathias Lesche <mathias.lesche@tu-dresden.de>, "Florian R. Hölzlwimmer" <git.ich@frhoelzlwimmer.de>, Till Hartmann <till.hartmann@bih-charite.de>, Thomas Sell <thomas.sell@bih-charite.de>, Travis Wrightsman <travis.wrightsman@uni-tuebingen.de>
License-File: LICENSE
Keywords: GRZ
Classifier: License :: OSI Approved :: MIT License
Classifier: Operating System :: OS Independent
Classifier: Programming Language :: Python :: 3
Requires-Python: >=3.12
Requires-Dist: pydantic<3,>=2.9.2
